{
  "main": {
    "id": "ff77fb9eddda1a66",
    "type": "split",
    "children": [
      {
        "id": "63fd10158b819792",
        "type": "tabs",
        "children": [
          {
            "id": "f5972a3bc8dd2913",
            "type": "leaf",
            "state": {
              "type": "markdown",
              "state": {
                "file": "Wiki/索引.md",
                "mode": "preview",
                "source": false
              },
              "icon": "lucide-file",
              "title": "索引"
            }
          }
        ]
      }
    ],
    "direction": "vertical"
  },
  "left": {
    "id": "d3d25bf490457d3f",
    "type": "split",
    "children": [
      {
        "id": "e9f44f3a215310f0",
        "type": "tabs",
        "children": [
          {
            "id": "afe508cb7288702b",
            "type": "leaf",
            "state": {
              "type": "file-explorer",
              "state": {
                "sortOrder": "alphabetical",
                "autoReveal": false
              },
              "icon": "lucide-folder-closed",
              "title": "檔案瀏覽器"
            }
          },
          {
            "id": "c8e1afe247f10a2c",
            "type": "leaf",
            "state": {
              "type": "search",
              "state": {
                "query": "",
                "matchingCase": false,
                "explainSearch": false,
                "collapseAll": false,
                "extraContext": false,
                "sortOrder": "alphabetical"
              },
              "icon": "lucide-search",
              "title": "搜尋"
            }
          },
          {
            "id": "e2cf6853af02223f",
            "type": "leaf",
            "state": {
              "type": "bookmarks",
              "state": {},
              "icon": "lucide-bookmark",
              "title": "書籤"
            }
          }
        ]
      }
    ],
    "direction": "horizontal",
    "width": 241.5
  },
  "right": {
    "id": "6c42056c421ee72a",
    "type": "split",
    "children": [
      {
        "id": "8f3167e12f70e457",
        "type": "tabs",
        "children": [
          {
            "id": "5bd7e3f19ead0af5",
            "type": "leaf",
            "state": {
              "type": "backlink",
              "state": {
                "file": "Wiki/Sources/肥宅老司機-S3EP197.md",
                "collapseAll": false,
                "extraContext": false,
                "sortOrder": "alphabetical",
                "showSearch": false,
                "searchQuery": "",
                "backlinkCollapsed": false,
                "unlinkedCollapsed": true
              },
              "icon": "links-coming-in",
              "title": "肥宅老司機-S3EP197 的反向連結"
            }
          },
          {
            "id": "20d82e0d226c4137",
            "type": "leaf",
            "state": {
              "type": "outgoing-link",
              "state": {
                "file": "Wiki/Sources/肥宅老司機-S3EP197.md",
                "linksCollapsed": false,
                "unlinkedCollapsed": true
              },
              "icon": "links-going-out",
              "title": "肥宅老司機-S3EP197 的對外連結"
            }
          },
          {
            "id": "d95cbb8cf8eba9ce",
            "type": "leaf",
            "state": {
              "type": "tag",
              "state": {
                "sortOrder": "frequency",
                "useHierarchy": true,
                "showSearch": false,
                "searchQuery": ""
              },
              "icon": "lucide-tags",
              "title": "標籤"
            }
          },
          {
            "id": "2662b755c3e2668d",
            "type": "leaf",
            "state": {
              "type": "all-properties",
              "state": {
                "sortOrder": "frequency",
                "showSearch": false,
                "searchQuery": ""
              },
              "icon": "lucide-archive",
              "title": "所有屬性"
            }
          },
          {
            "id": "3c4c0c7ab3b94793",
            "type": "leaf",
            "state": {
              "type": "outline",
              "state": {
                "file": "Wiki/Sources/肥宅老司機-S3EP197.md",
                "followCursor": false,
                "showSearch": false,
                "searchQuery": ""
              },
              "icon": "lucide-list",
              "title": "肥宅老司機-S3EP197 的大綱"
            }
          }
        ]
      }
    ],
    "direction": "horizontal",
    "width": 300,
    "collapsed": true
  },
  "left-ribbon": {
    "hiddenItems": {
      "switcher:開啟快速切換": false,
      "graph:查看關聯圖": false,
      "canvas:建立新畫布": false,
      "daily-notes:開啟今天的每日筆記": false,
      "templates:插入模板": false,
      "command-palette:開啟命令面板": false,
      "bases:建立新的 base": false,
      "workspaces:管理工作區配置": false,
      "markdown-importer:開啟 Markdown 格式轉換器": false
    }
  },
  "active": "f5972a3bc8dd2913",
  "lastOpenFiles": [
    "Wiki/人物/風俗娘娘.md",
    "HANDOVER.md.tmp.66356.1779188127660",
    "Wiki/店家/Paikanyai Bar.md",
    "Wiki/店家/Danika Massage.md",
    "Wiki/店家/Danika Massage.md.tmp.66356.1779188076027",
    "Wiki/概念/越南夜生活.md",
    "Wiki/概念/俄羅斯吧.md",
    "Wiki/概念/俄羅斯吧.md.tmp.66356.1779188033673",
    "Wiki/概念/人妖.md",
    "Wiki/概念/人妖.md.tmp.66356.1779188033283",
    "Wiki/來源/2025年5月芭提雅探店指南.md.tmp.66356.1779187989395",
    "Wiki/來源/2025年5月芭提雅探店指南.md.tmp.66356.1779187925124",
    "Wiki/人物/關生.md.tmp.66356.1779187920169",
    "HANDOVER.md.tmp.66356.1779187768549",
    "HANDOVER.md.tmp.66356.1779187754728",
    "HANDOVER.md.tmp.66356.1779187744800",
    "Wiki/地點/六巷.md",
    "Wiki/人物/阿哲.md",
    "Wiki/人物/阿威.md",
    "Wiki/人物/阿佳.md",
    "Wiki/人物/阿水.md",
    "Wiki/人物/老雞.md",
    "Wiki/人物/老濕.md",
    "Wiki/人物/老郭.md",
    "Wiki/人物/老張哥.md",
    "Wiki/人物/老爺.md",
    "Wiki/人物/打賽.md",
    "Wiki/人物/中年大叔貝斯手.md",
    "Wiki/人物/小銀蟲.md",
    "Wiki/人物/小韓.md",
    "Wiki/人物/小鑰匙.md",
    "Wiki/人物/大頭.md",
    "Wiki/人物/上海小林.md",
    "Wiki/人物/八爺.md",
    "Wiki/人物/YAPO.md",
    "Wiki/人物/Yuri.md",
    "肥宅老司機知識圖譜.png",
    "肥宅老司機知識圖譜 1.png",
    "肥宅老司機知識圖譜 2.png",
    "未命名.canvas"
  ]
}